buildout.cfg
changes.txt
setup.py
alchemist/__init__.py
alchemist.ui.egg-info/PKG-INFO
alchemist.ui.egg-info/SOURCES.txt
alchemist.ui.egg-info/dependency_links.txt
alchemist.ui.egg-info/namespace_packages.txt
alchemist.ui.egg-info/not-zip-safe
alchemist.ui.egg-info/requires.txt
alchemist.ui.egg-info/top_level.txt
alchemist/ui/__init__.py
alchemist/ui/configure.zcml
alchemist/ui/container.py
alchemist/ui/content.py
alchemist/ui/core.py
alchemist/ui/form.py
alchemist/ui/generic.py
alchemist/ui/i18n.py
alchemist/ui/interfaces.py
alchemist/ui/notes.txt
alchemist/ui/relation.py
alchemist/ui/traversable.py
alchemist/ui/viewlet.py
alchemist/ui/widgets.py
alchemist/ui/templates/content-edit.pt
alchemist/ui/templates/content-view.pt
alchemist/ui/templates/form.pt
alchemist/ui/templates/generic-container.pt
alchemist/ui/templates/one2one-unset.pt
alchemist/ui/templates/relation-edit.pt
alchemist/ui/templates/relation-view.pt
alchemist/ui/templates/subform.pt