Metadata-Version: 1.0
Name: alchemist.ui
Version: 0.4.2
Summary: user interface components for use with zope3 relational database applications, crud, listing and relation views
Home-page: UNKNOWN
Author: Kapil Thangavelu
Author-email: kapil.foss@gmail.com
License: LGPL
Keywords: zope zope3
Platform: UNKNOWN
Classifier: Programming Language :: Python
Classifier: Framework :: Zope3
